procodile/__init__.py
procodile/job.py
procodile/process.py
procodile/py.typed
procodile/registry.py
procodile/reporter.py
procodile/cli/__init__.py
procodile/cli/cli.py
procodile-0.0.8.dist-info/METADATA
procodile-0.0.8.dist-info/WHEEL
procodile-0.0.8.dist-info/licenses/LICENSE
procodile-0.0.8.dist-info/RECORD
