Metadata-Version: 2.4
Name: procodile
Version: 0.0.8
Summary: A light-weight processor development framework
Project-URL: Documentation, https://eo-tools.github.io/eozilla
Project-URL: Repository, https://github.com/eo-tools/eozilla
Project-URL: Changelog, https://github.com/eo-tools/eozilla/blob/main/CHANGES.md
Project-URL: Issues, https://github.com/eo-tools/eozilla/issues
Author: Norman Fomferra (Brockmann Consult GmbH), Tejas Morbagal Harish (Brockmann Consult GmbH)
License: Apache-2.0
License-File: LICENSE
Keywords: data processing,eo,esa,ogc
Classifier: Development Status :: 5 - Production/Stable
Classifier: Intended Audience :: Developers
Classifier: Intended Audience :: Science/Research
Classifier: License :: OSI Approved :: Apache Software License
Classifier: Operating System :: MacOS
Classifier: Operating System :: Microsoft :: Windows
Classifier: Operating System :: POSIX
Classifier: Operating System :: Unix
Classifier: Programming Language :: Python :: 3
Classifier: Programming Language :: Python :: 3.10
Classifier: Programming Language :: Python :: 3.11
Classifier: Programming Language :: Python :: 3.12
Classifier: Programming Language :: Python :: 3.13
Classifier: Topic :: Scientific/Engineering
Classifier: Topic :: Software Development
Classifier: Typing :: Typed
Requires-Python: >=3.10
Requires-Dist: gavicore>=0.0.7
Requires-Dist: pydantic
Requires-Dist: pyyaml
Requires-Dist: typer
